f_line_merger/main.py
f_line_merger-0.1.1.dist-info/METADATA
f_line_merger-0.1.1.dist-info/WHEEL
f_line_merger-0.1.1.dist-info/entry_points.txt
f_line_merger-0.1.1.dist-info/RECORD
